MANIFEST.in
README.rst
setup.py
pychatl/__init__.py
pychatl/augment.py
pychatl/cli.py
pychatl/entity_value_provider.py
pychatl/fp.py
pychatl/parser.py
pychatl/utils.py
pychatl/version.py
pychatl.egg-info/PKG-INFO
pychatl.egg-info/SOURCES.txt
pychatl.egg-info/dependency_links.txt
pychatl.egg-info/entry_points.txt
pychatl.egg-info/requires.txt
pychatl.egg-info/top_level.txt
pychatl/adapters/__init__.py
pychatl/adapters/rasa.py
pychatl/adapters/snips.py
tests/__init__.py
tests/test_augment.py
tests/test_entity_value_provider.py
tests/test_fp.py
tests/test_parser.py
tests/test_rasa.py
tests/test_snips.py
tests/test_utils.py