Metadata-Version: 2.1
Name: pychatl
Version: 2.0.1
Summary: Tiny DSL to generate training dataset for NLU engines
Home-page: https://github.com/atlassistant/chatl
Author: Julien LEICHER
License: GPL-3.0
Platform: UNKNOWN
Classifier: Programming Language :: Python :: 3
Classifier: Intended Audience :: Developers
Classifier: License :: OSI Approved :: MIT License
Provides-Extra: test
